pandas/__init__.py
pandas/_typing.py
pandas/_version.py
pandas/conftest.py
pandas/testing.py
pandas/_config/__init__.py
pandas/_config/config.py
pandas/_config/dates.py
pandas/_config/display.py
pandas/_config/localization.py
pandas/_libs/__init__.py
pandas/_libs/algos.cp311-win32.pyd
pandas/_libs/algos.pxd
pandas/_libs/algos.pyi
pandas/_libs/algos.pyx
pandas/_libs/algos_common_helper.pxi.in
pandas/_libs/algos_take_helper.pxi.in
pandas/_libs/arrays.cp311-win32.pyd
pandas/_libs/arrays.pxd
pandas/_libs/arrays.pyi
pandas/_libs/arrays.pyx
pandas/_libs/dtypes.pxd
pandas/_libs/groupby.cp311-win32.pyd
pandas/_libs/groupby.pyi
pandas/_libs/groupby.pyx
pandas/_libs/hashing.cp311-win32.pyd
pandas/_libs/hashing.pyi
pandas/_libs/hashing.pyx
pandas/_libs/hashtable.cp311-win32.pyd
pandas/_libs/hashtable.pxd
pandas/_libs/hashtable.pyi
pandas/_libs/hashtable.pyx
pandas/_libs/hashtable_class_helper.pxi.in
pandas/_libs/hashtable_func_helper.pxi.in
pandas/_libs/index.cp311-win32.pyd
pandas/_libs/index.pyi
pandas/_libs/index.pyx
pandas/_libs/index_class_helper.pxi.in
pandas/_libs/indexing.cp311-win32.pyd
pandas/_libs/indexing.pyi
pandas/_libs/indexing.pyx
pandas/_libs/internals.cp311-win32.pyd
pandas/_libs/internals.pyi
pandas/_libs/internals.pyx
pandas/_libs/interval.cp311-win32.pyd
pandas/_libs/interval.pyi
pandas/_libs/interval.pyx
pandas/_libs/intervaltree.pxi.in
pandas/_libs/join.cp311-win32.pyd
pandas/_libs/join.pyi
pandas/_libs/join.pyx
pandas/_libs/json.cp311-win32.pyd
pandas/_libs/json.pyi
pandas/_libs/khash.pxd
pandas/_libs/khash_for_primitive_helper.pxi.in
pandas/_libs/lib.cp311-win32.pyd
pandas/_libs/lib.pxd
pandas/_libs/lib.pyi
pandas/_libs/lib.pyx
pandas/_libs/missing.cp311-win32.pyd
pandas/_libs/missing.pxd
pandas/_libs/missing.pyi
pandas/_libs/missing.pyx
pandas/_libs/ops.cp311-win32.pyd
pandas/_libs/ops.pyi
pandas/_libs/ops.pyx
pandas/_libs/ops_dispatch.cp311-win32.pyd
pandas/_libs/ops_dispatch.pyi
pandas/_libs/ops_dispatch.pyx
pandas/_libs/parsers.cp311-win32.pyd
pandas-2.0.3.dist-info/AUTHORS.md
pandas-2.0.3.dist-info/LICENSE
pandas-2.0.3.dist-info/METADATA
pandas-2.0.3.dist-info/WHEEL
pandas-2.0.3.dist-info/entry_points.txt
pandas-2.0.3.dist-info/top_level.txt
pandas-2.0.3.dist-info/RECORD
