Metadata-Version: 2.1
Name: pandas
Version: 2.0.3
Summary: Powerful data structures for data analysis, time series, and statistics
Author-email: The Pandas Development Team <pandas-dev@python.org>
License: BSD 3-Clause License
Project-URL: homepage, https://pandas.pydata.org
Project-URL: documentation, https://pandas.pydata.org/docs/
Project-URL: repository, https://github.com/pandas-dev/pandas
Classifier: Development Status :: 5 - Production/Stable
Classifier: Environment :: Console
Classifier: Intended Audience :: Science/Research
Classifier: License :: OSI Approved :: BSD License
Classifier: Operating System :: OS Independent
Classifier: Programming Language :: Cython
Classifier: Programming Language :: Python
Classifier: Programming Language :: Python :: 3
Classifier: Programming Language :: Python :: 3 :: Only
Classifier: Programming Language :: Python :: 3.8
Classifier: Programming Language :: Python :: 3.9
Classifier: Programming Language :: Python :: 3.10
Classifier: Programming Language :: Python :: 3.11
Classifier: Topic :: Scientific/Engineering
Requires-Python: >=3.8
Provides-Extra: test
Provides-Extra: performance
Provides-Extra: computation
Provides-Extra: fss
Provides-Extra: aws
Provides-Extra: gcp
Provides-Extra: excel
Provides-Extra: parquet
Provides-Extra: feather
Provides-Extra: hdf5
Provides-Extra: spss
Provides-Extra: postgresql
Provides-Extra: mysql
Provides-Extra: sql-other
Provides-Extra: html
Provides-Extra: xml
Provides-Extra: plot
Provides-Extra: output_formatting
Provides-Extra: clipboard
Provides-Extra: compression
Provides-Extra: all
License-File: LICENSE
License-File: AUTHORS.md
